MANIFEST.in
README.md
pypi.rst
setup.py
version
hashcat/__init__.py
hashcat/cli.py
hashcat/hashcat/example.dict
hashcat/hashcat/example0.cmd
hashcat/hashcat/example0.hash
hashcat/hashcat/example0.sh
hashcat/hashcat/example400.cmd
hashcat/hashcat/example400.hash
hashcat/hashcat/example400.sh
hashcat/hashcat/example500.cmd
hashcat/hashcat/example500.hash
hashcat/hashcat/example500.sh
hashcat/hashcat/hashcat.bin
hashcat/hashcat/hashcat.exe
hashcat/hashcat/hashcat.hcstat2
hashcat/hashcat/hashcat.hctune
hashcat/hashcat/OpenCL/amp_a0.cl
hashcat/hashcat/OpenCL/amp_a1.cl
hashcat/hashcat/OpenCL/amp_a3.cl
hashcat/hashcat/OpenCL/inc_cipher_aes.cl
hashcat/hashcat/OpenCL/inc_cipher_aes.h
hashcat/hashcat/OpenCL/inc_cipher_camellia.cl
hashcat/hashcat/OpenCL/inc_cipher_camellia.h
hashcat/hashcat/OpenCL/inc_cipher_des.cl
hashcat/hashcat/OpenCL/inc_cipher_des.h
hashcat/hashcat/OpenCL/inc_cipher_kuznyechik.cl
hashcat/hashcat/OpenCL/inc_cipher_kuznyechik.h
hashcat/hashcat/OpenCL/inc_cipher_serpent.cl
hashcat/hashcat/OpenCL/inc_cipher_serpent.h
hashcat/hashcat/OpenCL/inc_cipher_twofish.cl
hashcat/hashcat/OpenCL/inc_cipher_twofish.h
hashcat/hashcat/OpenCL/inc_common.cl
hashcat/hashcat/OpenCL/inc_common.h
hashcat/hashcat/OpenCL/inc_comp_multi.cl
hashcat/hashcat/OpenCL/inc_comp_multi.h
hashcat/hashcat/OpenCL/inc_comp_multi_bs.cl
hashcat/hashcat/OpenCL/inc_comp_multi_bs.h
hashcat/hashcat/OpenCL/inc_comp_single.cl
hashcat/hashcat/OpenCL/inc_comp_single.h
hashcat/hashcat/OpenCL/inc_comp_single_bs.cl
hashcat/hashcat/OpenCL/inc_comp_single_bs.h
hashcat/hashcat/OpenCL/inc_diskcryptor_xts.cl
hashcat/hashcat/OpenCL/inc_diskcryptor_xts.h
hashcat/hashcat/OpenCL/inc_ecc_secp256k1.cl
hashcat/hashcat/OpenCL/inc_ecc_secp256k1.h
hashcat/hashcat/OpenCL/inc_hash_md4.cl
hashcat/hashcat/OpenCL/inc_hash_md4.h
hashcat/hashcat/OpenCL/inc_hash_md5.cl
hashcat/hashcat/OpenCL/inc_hash_md5.h
hashcat/hashcat/OpenCL/inc_hash_ripemd160.cl
hashcat/hashcat/OpenCL/inc_hash_ripemd160.h
hashcat_beta.egg-info/PKG-INFO
hashcat_beta.egg-info/SOURCES.txt
hashcat_beta.egg-info/dependency_links.txt
hashcat_beta.egg-info/entry_points.txt
hashcat_beta.egg-info/requires.txt
hashcat_beta.egg-info/top_level.txt